{"id":"main.js","dependencies":[],"generated":{"js":"var html = document.querySelector(\"#html\");\nvar style = document.querySelector('#style');\n\nvar string = \"/*\\u4F60\\u597D\\u5440!,\\u563B~\\u563B\\n\\u63A5\\u4E0B\\u6765\\u8BA9\\u4F60\\u7785\\u7785\\u6211\\u8FD9\\u4F1A\\u5199\\u7684\\u4EE3\\u7801\\n\\u9996\\u5148\\u6211\\u51C6\\u5907\\u4E00\\u4E2Adiv\\uFF1A*/\\n#div1{\\n    border:1px solid red;\\n    width:200px;\\n    height:200px;\\n    position: fixed;\\n    left:50%;\\n    transform:translateX(-50%);\\n    top:20px;\\n}\\n/*\\n\\u63A5\\u4E0B\\u6765\\u6211\\u4EEC\\u628Adiv\\u53D8\\u6210\\u4E00\\u4E2A\\u516B\\u5366\\n\\u5F00\\u59CB\\u5566\\n\\u9996\\u5148\\uFF0C\\u628Adiv\\u53D8\\u6210\\u4E00\\u4E2A\\u5706\\n*/\\n#div1{\\n    border-radius:50%;\\n    box-shadow:0 0 3px rgba(0,0,0,0.5);\\n    border:none;\\n} \\n/*\\n\\u516B\\u5366\\u8BB2\\u7684\\u662F\\u4E00\\u4E2A\\u9634\\u9633\\u2014\\u2014\\u2014\\u2014\\n\\u4E00\\u9ED1\\u4E00\\u767D\\n*/\\n#div1{\\n    background:linear-gradient(90deg,rgba(255,255,255,1)0%,\\n    rgba(255,255,255,1) 50%,rgba(0,0,0,1)50%,rgba(0,0,0,1)100%);\\n}\\n#div1::before{\\n    content:'';\\n    display:block;\\n    position:absolute;\\n} \\n#div1::after{\\n    content:'';\\n    display:block;\\n    position:absolute;\\n}\\n/*\\n\\u63A5\\u4E0B\\u6765\\u52A0\\u4E24\\u4E2A\\u54C7\\u5440\\u5440\\u901B\\u901B\\u5C91\\u9B54\\u6CD5\\u667A\\u6167\\u7403\\uFF1A\\n*/\\n#div1::before{\\n    width:100px;\\n    height:100px;\\n    top:0;\\n    left:50%;\\n    transform:translateX(-50%);\\n    background:#000;\\n    border-radius:50%;\\n    background:radial-gradient(circle,rgba(255,255,255,1)0%,rgba(255, 255,255,1)25%, rgba(0,0,0,1)25%,rgba(0,0,0,1)100%);\\n}\\n#div1::after{\\n    width:100px;\\n    height:100px;\\n    bottom:0;\\n    left:50%;\\n    transform:translateX(-50%);\\n    background:#fff;\\n    border-radius:50%;\\n    background:radial-gradient(circle,rgba(0,0,0,1)0%,rgba(0,0,0,1)25%,rgba(255,255,255,1)25%,rgba(255,255,255,1)100%,rgba(0,0,0,1)100%);\\n}\\n/*\\nOK\\u521D\\u6B65\\u516B\\u5366\\u5C31\\u5148\\u641E\\u5B9A\\u5566\\n*/\\n\";\n\nvar string2 = \"\";\n\nvar n = 0;\n\nvar step = function step() {\n    setTimeout(function () {\n        //判断string内容是哪个是空格\n        if (string[n] === \"\\n\") {\n            string2 += \"<br>\";\n        } else if (string[n] === \" \") {\n            string2 += \"&nbsp;\";\n        } else {\n            string2 += string[n];\n        }\n\n        if (n + 1 < string.length) {\n            step();\n            n += 1;\n        }\n\n        html.innerHTML = string2;\n        style.innerHTML = string.substring(0, n);\n        window.scrollTo(0, 9999);\n        html.scrollTo(0, 9999);\n    }, 50);\n};\nstep();","map":{"mappings":[{"generated":{"line":1,"column":0},"source":"main.js","original":{"line":1,"column":0}},{"name":"html","generated":{"line":1,"column":4},"source":"main.js","original":{"line":1,"column":4}},{"name":"document","generated":{"line":1,"column":11},"source":"main.js","original":{"line":1,"column":11}},{"name":"querySelector","generated":{"line":1,"column":20},"source":"main.js","original":{"line":1,"column":20}},{"generated":{"line":1,"column":33},"source":"main.js","original":{"line":1,"column":11}},{"generated":{"line":1,"column":34},"source":"main.js","original":{"line":1,"column":34}},{"generated":{"line":1,"column":41},"source":"main.js","original":{"line":1,"column":11}},{"generated":{"line":1,"column":42},"source":"main.js","original":{"line":1,"column":0}},{"generated":{"line":2,"column":0},"source":"main.js","original":{"line":2,"column":0}},{"name":"style","generated":{"line":2,"column":4},"source":"main.js","original":{"line":2,"column":4}},{"name":"document","generated":{"line":2,"column":12},"source":"main.js","original":{"line":2,"column":12}},{"name":"querySelector","generated":{"line":2,"column":21},"source":"main.js","original":{"line":2,"column":21}},{"generated":{"line":2,"column":34},"source":"main.js","original":{"line":2,"column":12}},{"generated":{"line":2,"column":35},"source":"main.js","original":{"line":2,"column":35}},{"generated":{"line":2,"column":43},"source":"main.js","original":{"line":2,"column":12}},{"generated":{"line":2,"column":44},"source":"main.js","original":{"line":2,"column":0}},{"generated":{"line":4,"column":0},"source":"main.js","original":{"line":4,"column":0}},{"name":"string","generated":{"line":4,"column":4},"source":"main.js","original":{"line":4,"column":4}},{"generated":{"line":4,"column":1796},"source":"main.js","original":{"line":4,"column":0}},{"generated":{"line":6,"column":0},"source":"main.js","original":{"line":72,"column":0}},{"name":"string2","generated":{"line":6,"column":4},"source":"main.js","original":{"line":72,"column":4}},{"generated":{"line":6,"column":14},"source":"main.js","original":{"line":72,"column":14}},{"generated":{"line":6,"column":16},"source":"main.js","original":{"line":72,"column":0}},{"generated":{"line":8,"column":0},"source":"main.js","original":{"line":74,"column":0}},{"name":"n","generated":{"line":8,"column":4},"source":"main.js","original":{"line":74,"column":4}},{"generated":{"line":8,"column":8},"source":"main.js","original":{"line":74,"column":8}},{"generated":{"line":8,"column":9},"source":"main.js","original":{"line":74,"column":0}},{"generated":{"line":10,"column":0},"source":"main.js","original":{"line":77,"column":0}},{"name":"step","generated":{"line":10,"column":4},"source":"main.js","original":{"line":77,"column":4}},{"generated":{"line":10,"column":11},"source":"main.js","original":{"line":77,"column":11}},{"name":"step","generated":{"line":10,"column":20},"source":"main.js","original":{"line":77,"column":4}},{"generated":{"line":10,"column":24},"source":"main.js","original":{"line":77,"column":11}},{"generated":{"line":10,"column":27},"source":"main.js","original":{"line":77,"column":17}},{"name":"setTimeout","generated":{"line":11,"column":0},"source":"main.js","original":{"line":78,"column":1}},{"generated":{"line":11,"column":15},"source":"main.js","original":{"line":78,"column":12}},{"generated":{"line":11,"column":27},"source":"main.js","original":{"line":78,"column":18}},{"generated":{"line":12,"column":0},"source":"main.js","original":{"line":79,"column":2}},{"generated":{"line":13,"column":0},"source":"main.js","original":{"line":80,"column":2}},{"name":"string","generated":{"line":13,"column":12},"source":"main.js","original":{"line":80,"column":6}},{"name":"n","generated":{"line":13,"column":19},"source":"main.js","original":{"line":80,"column":13}},{"generated":{"line":13,"column":20},"source":"main.js","original":{"line":80,"column":6}},{"generated":{"line":13,"column":26},"source":"main.js","original":{"line":80,"column":20}},{"generated":{"line":13,"column":30},"source":"main.js","original":{"line":80,"column":2}},{"generated":{"line":13,"column":32},"source":"main.js","original":{"line":80,"column":26}},{"name":"string2","generated":{"line":14,"column":0},"source":"main.js","original":{"line":81,"column":3}},{"generated":{"line":14,"column":23},"source":"main.js","original":{"line":81,"column":14}},{"generated":{"line":14,"column":29},"source":"main.js","original":{"line":81,"column":3}},{"generated":{"line":15,"column":0},"source":"main.js","original":{"line":82,"column":3}},{"generated":{"line":15,"column":9},"source":"main.js","original":{"line":80,"column":2}},{"generated":{"line":15,"column":15},"source":"main.js","original":{"line":82,"column":9}},{"name":"string","generated":{"line":15,"column":19},"source":"main.js","original":{"line":82,"column":13}},{"name":"n","generated":{"line":15,"column":26},"source":"main.js","original":{"line":82,"column":20}},{"generated":{"line":15,"column":27},"source":"main.js","original":{"line":82,"column":13}},{"generated":{"line":15,"column":33},"source":"main.js","original":{"line":82,"column":27}},{"generated":{"line":15,"column":36},"source":"main.js","original":{"line":82,"column":9}},{"generated":{"line":15,"column":38},"source":"main.js","original":{"line":82,"column":32}},{"name":"string2","generated":{"line":16,"column":0},"source":"main.js","original":{"line":83,"column":3}},{"generated":{"line":16,"column":23},"source":"main.js","original":{"line":83,"column":14}},{"generated":{"line":16,"column":31},"source":"main.js","original":{"line":83,"column":3}},{"generated":{"line":17,"column":0},"source":"main.js","original":{"line":84,"column":3}},{"generated":{"line":17,"column":9},"source":"main.js","original":{"line":82,"column":9}},{"generated":{"line":17,"column":15},"source":"main.js","original":{"line":84,"column":9}},{"name":"string2","generated":{"line":18,"column":0},"source":"main.js","original":{"line":85,"column":3}},{"name":"string","generated":{"line":18,"column":23},"source":"main.js","original":{"line":85,"column":14}},{"name":"n","generated":{"line":18,"column":30},"source":"main.js","original":{"line":85,"column":21}},{"generated":{"line":18,"column":31},"source":"main.js","original":{"line":85,"column":14}},{"generated":{"line":18,"column":32},"source":"main.js","original":{"line":85,"column":3}},{"generated":{"line":19,"column":0},"source":"main.js","original":{"line":86,"column":3}},{"generated":{"line":21,"column":0},"source":"main.js","original":{"line":88,"column":2}},{"name":"n","generated":{"line":21,"column":12},"source":"main.js","original":{"line":88,"column":6}},{"generated":{"line":21,"column":16},"source":"main.js","original":{"line":88,"column":10}},{"generated":{"line":21,"column":17},"source":"main.js","original":{"line":88,"column":6}},{"name":"string","generated":{"line":21,"column":20},"source":"main.js","original":{"line":88,"column":14}},{"name":"length","generated":{"line":21,"column":27},"source":"main.js","original":{"line":88,"column":21}},{"generated":{"line":21,"column":33},"source":"main.js","original":{"line":88,"column":2}},{"generated":{"line":21,"column":35},"source":"main.js","original":{"line":88,"column":29}},{"name":"step","generated":{"line":22,"column":0},"source":"main.js","original":{"line":89,"column":3}},{"name":"n","generated":{"line":23,"column":0},"source":"main.js","original":{"line":90,"column":3}},{"generated":{"line":23,"column":17},"source":"main.js","original":{"line":90,"column":8}},{"generated":{"line":23,"column":18},"source":"main.js","original":{"line":90,"column":3}},{"generated":{"line":24,"column":0},"source":"main.js","original":{"line":91,"column":3}},{"name":"html","generated":{"line":26,"column":0},"source":"main.js","original":{"line":93,"column":2}},{"name":"innerHTML","generated":{"line":26,"column":13},"source":"main.js","original":{"line":93,"column":7}},{"generated":{"line":26,"column":22},"source":"main.js","original":{"line":93,"column":2}},{"name":"string2","generated":{"line":26,"column":25},"source":"main.js","original":{"line":93,"column":19}},{"generated":{"line":26,"column":32},"source":"main.js","original":{"line":93,"column":2}},{"name":"style","generated":{"line":27,"column":0},"source":"main.js","original":{"line":94,"column":2}},{"name":"innerHTML","generated":{"line":27,"column":14},"source":"main.js","original":{"line":94,"column":8}},{"generated":{"line":27,"column":23},"source":"main.js","original":{"line":94,"column":2}},{"name":"string","generated":{"line":27,"column":26},"source":"main.js","original":{"line":94,"column":20}},{"name":"substring","generated":{"line":27,"column":33},"source":"main.js","original":{"line":94,"column":27}},{"generated":{"line":27,"column":42},"source":"main.js","original":{"line":94,"column":20}},{"generated":{"line":27,"column":43},"source":"main.js","original":{"line":94,"column":37}},{"generated":{"line":27,"column":44},"source":"main.js","original":{"line":94,"column":20}},{"name":"n","generated":{"line":27,"column":46},"source":"main.js","original":{"line":94,"column":40}},{"generated":{"line":27,"column":47},"source":"main.js","original":{"line":94,"column":20}},{"generated":{"line":27,"column":48},"source":"main.js","original":{"line":94,"column":2}},{"name":"window","generated":{"line":28,"column":0},"source":"main.js","original":{"line":95,"column":2}},{"name":"scrollTo","generated":{"line":28,"column":15},"source":"main.js","original":{"line":95,"column":9}},{"generated":{"line":28,"column":23},"source":"main.js","original":{"line":95,"column":2}},{"generated":{"line":28,"column":24},"source":"main.js","original":{"line":95,"column":18}},{"generated":{"line":28,"column":25},"source":"main.js","original":{"line":95,"column":2}},{"generated":{"line":28,"column":27},"source":"main.js","original":{"line":95,"column":21}},{"generated":{"line":28,"column":31},"source":"main.js","original":{"line":95,"column":2}},{"name":"html","generated":{"line":29,"column":0},"source":"main.js","original":{"line":96,"column":2}},{"name":"scrollTo","generated":{"line":29,"column":13},"source":"main.js","original":{"line":96,"column":7}},{"generated":{"line":29,"column":21},"source":"main.js","original":{"line":96,"column":2}},{"generated":{"line":29,"column":22},"source":"main.js","original":{"line":96,"column":16}},{"generated":{"line":29,"column":23},"source":"main.js","original":{"line":96,"column":2}},{"generated":{"line":29,"column":25},"source":"main.js","original":{"line":96,"column":19}},{"generated":{"line":29,"column":29},"source":"main.js","original":{"line":96,"column":2}},{"generated":{"line":30,"column":0},"source":"main.js","original":{"line":97,"column":2}},{"generated":{"line":30,"column":5},"source":"main.js","original":{"line":78,"column":1}},{"generated":{"line":30,"column":7},"source":"main.js","original":{"line":97,"column":4}},{"generated":{"line":30,"column":9},"source":"main.js","original":{"line":78,"column":1}},{"generated":{"line":31,"column":0},"source":"main.js","original":{"line":99,"column":1}},{"generated":{"line":31,"column":1},"source":"main.js","original":{"line":77,"column":0}},{"name":"step","generated":{"line":32,"column":0},"source":"main.js","original":{"line":100,"column":0}}],"sources":{"main.js":"let html = document.querySelector(\"#html\")\r\nlet style = document.querySelector('#style')\r\n\r\nlet string = `/*你好呀!,嘻~嘻\r\n接下来让你瞅瞅我这会写的代码\r\n首先我准备一个div：*/\r\n#div1{\r\n    border:1px solid red;\r\n    width:200px;\r\n    height:200px;\r\n    position: fixed;\r\n    left:50%;\r\n    transform:translateX(-50%);\r\n    top:20px;\r\n}\r\n/*\r\n接下来我们把div变成一个八卦\r\n开始啦\r\n首先，把div变成一个圆\r\n*/\r\n#div1{\r\n    border-radius:50%;\r\n    box-shadow:0 0 3px rgba(0,0,0,0.5);\r\n    border:none;\r\n} \r\n/*\r\n八卦讲的是一个阴阳————\r\n一黑一白\r\n*/\r\n#div1{\r\n    background:linear-gradient(90deg,rgba(255,255,255,1)0%,\r\n    rgba(255,255,255,1) 50%,rgba(0,0,0,1)50%,rgba(0,0,0,1)100%);\r\n}\r\n#div1::before{\r\n    content:'';\r\n    display:block;\r\n    position:absolute;\r\n} \r\n#div1::after{\r\n    content:'';\r\n    display:block;\r\n    position:absolute;\r\n}\r\n/*\r\n接下来加两个哇呀呀逛逛岑魔法智慧球：\r\n*/\r\n#div1::before{\r\n    width:100px;\r\n    height:100px;\r\n    top:0;\r\n    left:50%;\r\n    transform:translateX(-50%);\r\n    background:#000;\r\n    border-radius:50%;\r\n    background:radial-gradient(circle,rgba(255,255,255,1)0%,rgba(255, 255,255,1)25%, rgba(0,0,0,1)25%,rgba(0,0,0,1)100%);\r\n}\r\n#div1::after{\r\n    width:100px;\r\n    height:100px;\r\n    bottom:0;\r\n    left:50%;\r\n    transform:translateX(-50%);\r\n    background:#fff;\r\n    border-radius:50%;\r\n    background:radial-gradient(circle,rgba(0,0,0,1)0%,rgba(0,0,0,1)25%,rgba(255,255,255,1)25%,rgba(255,255,255,1)100%,rgba(0,0,0,1)100%);\r\n}\r\n/*\r\nOK初步八卦就先搞定啦\r\n*/\r\n`;\r\n\r\nlet string2 = \"\";\r\n\r\nlet n = 0;\r\n\r\n\r\nlet step = () => {\r\n\tsetTimeout(() => {\r\n\t\t//判断string内容是哪个是空格\r\n\t\tif (string[n] === \"\\n\") {\r\n\t\t\tstring2 += \"<br>\";\r\n\t\t} else if (string[n] === \" \") {\r\n\t\t\tstring2 += \"&nbsp;\";\r\n\t\t} else {\r\n\t\t\tstring2 += string[n];\r\n\t\t}\r\n\r\n\t\tif (n + 1 < string.length) {\r\n\t\t\tstep()\r\n\t\t\tn += 1;\r\n\t\t}\r\n\r\n\t\thtml.innerHTML = string2;\r\n\t\tstyle.innerHTML = string.substring(0, n);\r\n\t\twindow.scrollTo(0, 9999);\r\n\t\thtml.scrollTo(0, 9999)\r\n\t}, 50);\r\n\r\n}\r\nstep();\r\n"},"lineCount":null}},"hash":"ea6eaf28e868e956f09001625cf9a0d1","cacheData":{"env":{}}}